flattenit/__init__.py
flattenit/cli.py
flattenit/flattenit.py
flattenit-0.2.6.dist-info/AUTHORS.rst
flattenit-0.2.6.dist-info/LICENSE
flattenit-0.2.6.dist-info/METADATA
flattenit-0.2.6.dist-info/WHEEL
flattenit-0.2.6.dist-info/entry_points.txt
flattenit-0.2.6.dist-info/top_level.txt
flattenit-0.2.6.dist-info/RECORD
