Metadata-Version: 2.1
Name: flattenit
Version: 0.2.6
Summary: Flatten a 2D list of lists
Home-page: https://github.com/purpleviolet/flattenit
Author: Diane Chen
Author-email: purplediane.chen@gmail.com
License: MIT license
Keywords: flattenit
Platform: UNKNOWN
Classifier: Development Status :: 2 - Pre-Alpha
Classifier: Intended Audience :: Developers
Classifier: License :: OSI Approved :: MIT License
Classifier: Natural Language :: English
Classifier: Programming Language :: Python :: 2
Classifier: Programming Language :: Python :: 2.7
Classifier: Programming Language :: Python :: 3
Classifier: Programming Language :: Python :: 3.4
Classifier: Programming Language :: Python :: 3.5
Classifier: Programming Language :: Python :: 3.6
Classifier: Programming Language :: Python :: 3.7
Requires-Dist: Click (>=6.0)
